evobench/__init__.py
evobench/benchmark.py
evobench/initialization.py
evobench/separable.py
evobench/util.py
evobench/continuous/__init__.py
evobench/continuous/multimodal.py
evobench/continuous/sawtooth.py
evobench/continuous/step_multimodal.py
evobench/continuous/trap.py
evobench/continuous/initialization/__init__.py
evobench/continuous/initialization/uniform.py
evobench/continuous/initialization/test/__init__.py
evobench/continuous/initialization/test/test_uniform.py
evobench/continuous/test/__init__.py
evobench/continuous/test/test_multimodal.py
evobench/continuous/test/test_sawtooth.py
evobench/continuous/test/test_step_multimodal.py
evobench/continuous/test/test_trap.py
evobench/discrete/__init__.py
evobench/discrete/bimodal.py
evobench/discrete/hiff.py
evobench/discrete/hiff_star.py
evobench/discrete/step_bimodal.py
evobench/discrete/step_trap.py
evobench/discrete/trap.py
evobench/discrete/initialization/__init__.py
evobench/discrete/initialization/complete.py
evobench/discrete/initialization/uniform.py
evobench/discrete/initialization/test/__init__.py
evobench/discrete/initialization/test/test_complete.py
evobench/discrete/initialization/test/test_sample.py
evobench/discrete/isg/__init__.py
evobench/discrete/isg/config.py
evobench/discrete/isg/isg.py
evobench/discrete/isg/parser.py
evobench/discrete/isg/spin.py
evobench/discrete/isg/test/__init__.py
evobench/discrete/isg/test/test_isg.py
evobench/discrete/test/__init__.py
evobench/discrete/test/test_bimodal.py
evobench/discrete/test/test_hiff.py
evobench/discrete/test/test_hiff_star.py
evobench/discrete/test/test_step_bimodal.py
evobench/discrete/test/test_step_trap.py
evobench/discrete/test/test_trap.py
evobench/model/__init__.py
evobench/model/population.py
evobench/model/solution.py
evobench/test/__init__.py
evobench/test/test_separable.py
evobench-0.0.3.dist-info/LICENSE
evobench-0.0.3.dist-info/METADATA
evobench-0.0.3.dist-info/WHEEL
evobench-0.0.3.dist-info/top_level.txt
evobench-0.0.3.dist-info/RECORD
