Metadata-Version: 2.1
Name: evobench
Version: 0.0.3
Summary: Benchmarks for large scale, model-based optimization.
Home-page: https://github.com/piotr-rarus/evobench
Author: Piotr Rarus
Author-email: piotr.rarus@gmail.com
License: MIT
Platform: UNKNOWN
Classifier: Programming Language :: Python :: 3
Classifier: License :: OSI Approved :: MIT License
Classifier: Operating System :: OS Independent
Requires-Dist: numpy
Requires-Dist: sympy
Requires-Dist: lazy
Requires-Dist: tqdm
